appa/__init__.py
appa/propagator.py
appa/solarsystem.py
appa/spacecraft.py
appa/stop_conditions.py
appa/toolbox.py
appa/spice_data/de432s.bsp
appa/spice_data/latest_leapseconds.tls
appa-0.4.2.dist-info/METADATA
appa-0.4.2.dist-info/WHEEL
appa-0.4.2.dist-info/licenses/LICENSE
appa-0.4.2.dist-info/RECORD
