Metadata-Version: 2.1
Name: appa
Version: 0.4.2
Project-URL: Homepage, https://github.com/coope248/APPA
Project-URL: Bug Tracker, https://github.com/coope248/APPA/issues
Author: C. Cooper
License-File: LICENSE
Classifier: License :: OSI Approved :: Apache Software License
Classifier: Operating System :: OS Independent
Classifier: Programming Language :: Python :: 3
Classifier: Topic :: Scientific/Engineering :: Physics
Classifier: Topic :: Scientific/Engineering :: Visualization
Requires-Python: >=3.7
Requires-Dist: numpy
Requires-Dist: pandas
Requires-Dist: plotly
Requires-Dist: scipy
Requires-Dist: spiceypy
